[
  {
    "region": "Provence-Alpes-Côte d'Azur",
    "sondages": [
      {
        "id": "20210603_paca_ips",
        "nom_institut": "Ipsos",
        "debut_enquete": "2021-06-03",
        "fin_enquete": "2021-06-07",
        "commanditaire": "France 3",
        "lien": "http://www.commission-des-sondages.fr/notices/files/notices/2021/juin/9164-paca-ipsos-france-tv.pdf",
        "echantillon": 398,
        "population": "Certains d'aller voter",
        "tours": [
          {
            "tour": "Premier tour",
            "hypotheses": [
              {
                "hypothese": null,
                "sous_echantillon": 362.18,
                "tetes_liste": [
                  {
                    "tete_liste": "Hervé Guerrera",
                    "parti": {},
                    "intentions": 1,
                    "erreur_sup": 2.0247,
                    "erreur_inf": 0
                  },
                  {
                    "tete_liste": "Jean-Laurent Felizia",
                    "parti": [
                      "EE-LV",
                      "Parti socialiste",
                      "Parti communiste",
                      "Génération·s"
                    ],
                    "intentions": 15,
                    "erreur_sup": 18.6775,
                    "erreur_inf": 11.3225
                  },
                  {
                    "tete_liste": "Renaud Muselier",
                    "parti": [
                      "UDI",
                      "Les Républicains",
                      "LRM",
                      "Modem",
                      "Agir"
                    ],
                    "intentions": 34,
                    "erreur_sup": 38.8787,
                    "erreur_inf": 29.1213
                  },
                  {
                    "tete_liste": "Isabelle Bonnet",
                    "parti": "Lutte ouvrière",
                    "intentions": 2,
                    "erreur_sup": 3.4419,
                    "erreur_inf": 0.5581
                  },
                  {
                    "tete_liste": "Valérie Laupies",
                    "parti": {},
                    "intentions": 1,
                    "erreur_sup": 2.0247,
                    "erreur_inf": 0
                  },
                  {
                    "tete_liste": "Thierry Mariani",
                    "parti": "Rassemblement national",
                    "intentions": 41,
                    "erreur_sup": 46.0654,
                    "erreur_inf": 35.9346
                  },
                  {
                    "tete_liste": "Noël Chuisano",
                    "parti": "Debout la France",
                    "intentions": 2,
                    "erreur_sup": 3.4419,
                    "erreur_inf": 0.5581
                  },
                  {
                    "tete_liste": "Jean-Marc Governatori",
                    "parti": "Cap écologie",
                    "intentions": 3,
                    "erreur_sup": 4.7569,
                    "erreur_inf": 1.2431
                  },
                  {
                    "tete_liste": "Mikael Vicenzi",
                    "parti": {},
                    "intentions": 1,
                    "erreur_sup": 2.0247,
                    "erreur_inf": 0
                  }
                ]
              }
            ]
          },
          {
            "tour": "Deuxième tour",
            "hypotheses": [
              {
                "hypothese": "Hypothèse triangulaire",
                "sous_echantillon": 362.18,
                "tetes_liste": [
                  {
                    "tete_liste": "Thierry Mariani",
                    "parti": "Rassemblement national",
                    "intentions": 43,
                    "erreur_sup": 48.0988,
                    "erreur_inf": 37.9012
                  },
                  {
                    "tete_liste": "Renaud Muselier",
                    "parti": [
                      "UDI",
                      "Les Républicains",
                      "LRM",
                      "Modem",
                      "Agir"
                    ],
                    "intentions": 36,
                    "erreur_sup": 40.9435,
                    "erreur_inf": 31.0565
                  },
                  {
                    "tete_liste": "Jean-Laurent Felizia",
                    "parti": [
                      "EE-LV",
                      "Parti socialiste",
                      "Parti communiste",
                      "Génération·s"
                    ],
                    "intentions": 21,
                    "erreur_sup": 25.1949,
                    "erreur_inf": 16.8051
                  }
                ]
              },
              {
                "hypothese": "Hypothèse duel",
                "sous_echantillon": 322.38,
                "tetes_liste": [
                  {
                    "tete_liste": "Thierry Mariani",
                    "parti": "Rassemblement national",
                    "intentions": 51,
                    "erreur_sup": 56.457,
                    "erreur_inf": 45.543
                  },
                  {
                    "tete_liste": "Renaud Muselier",
                    "parti": [
                      "UDI",
                      "Les Républicains",
                      "LRM",
                      "Modem",
                      "Agir"
                    ],
                    "intentions": 49,
                    "erreur_sup": 54.457,
                    "erreur_inf": 43.543
                  }
                ]
              }
            ]
          }
        ]
      },
      {
        "id": "20210610_paca_ifp",
        "nom_institut": "Ifop",
        "debut_enquete": "2021-06-10",
        "fin_enquete": "2021-06-14",
        "commanditaire": "LCI et Le Figaro",
        "lien": "http://www.commission-des-sondages.fr/notices/files/notices/2021/juin/9180-paca-ifop-le-figaro.pdf",
        "echantillon": 960,
        "population": "Inscrits sur les listes électorales",
        "tours": [
          {
            "tour": "Deuxième tour",
            "hypotheses": [
              {
                "hypothese": "Hypothèse duel",
                "sous_echantillon": 637.44,
                "tetes_liste": [
                  {
                    "tete_liste": "Thierry Mariani",
                    "parti": "Rassemblement national",
                    "intentions": 51,
                    "erreur_sup": 54.8808,
                    "erreur_inf": 47.1192
                  },
                  {
                    "tete_liste": "Renaud Muselier",
                    "parti": [
                      "UDI",
                      "Les Républicains",
                      "LRM",
                      "Modem",
                      "Agir"
                    ],
                    "intentions": 49,
                    "erreur_sup": 52.8808,
                    "erreur_inf": 45.1192
                  }
                ]
              },
              {
                "hypothese": "Hypothèse triangulaire",
                "sous_echantillon": 699.84,
                "tetes_liste": [
                  {
                    "tete_liste": "Renaud Muselier",
                    "parti": [
                      "UDI",
                      "Les Républicains",
                      "LRM",
                      "Modem",
                      "Agir"
                    ],
                    "intentions": 36,
                    "erreur_sup": 39.5563,
                    "erreur_inf": 32.4437
                  },
                  {
                    "tete_liste": "Jean-Laurent Felizia",
                    "parti": [
                      "EE-LV",
                      "Parti socialiste",
                      "Parti communiste",
                      "Génération·s"
                    ],
                    "intentions": 20,
                    "erreur_sup": 22.9636,
                    "erreur_inf": 17.0364
                  },
                  {
                    "tete_liste": "Thierry Mariani",
                    "parti": "Rassemblement national",
                    "intentions": 44,
                    "erreur_sup": 47.6777,
                    "erreur_inf": 40.3223
                  }
                ]
              }
            ]
          },
          {
            "tour": "Premier tour",
            "hypotheses": [
              {
                "hypothese": null,
                "sous_echantillon": 690.24,
                "tetes_liste": [
                  {
                    "tete_liste": "Isabelle Bonnet",
                    "parti": "Lutte ouvrière",
                    "intentions": 1,
                    "erreur_sup": 1.7423,
                    "erreur_inf": 0.2577
                  },
                  {
                    "tete_liste": "Renaud Muselier",
                    "parti": [
                      "UDI",
                      "Les Républicains",
                      "LRM",
                      "Modem",
                      "Agir"
                    ],
                    "intentions": 34,
                    "erreur_sup": 37.534,
                    "erreur_inf": 30.466
                  },
                  {
                    "tete_liste": "Thierry Mariani",
                    "parti": "Rassemblement national",
                    "intentions": 41,
                    "erreur_sup": 44.6692,
                    "erreur_inf": 37.3308
                  },
                  {
                    "tete_liste": "Noël Chuisano",
                    "parti": "Debout la France",
                    "intentions": 3,
                    "erreur_sup": 4.2726,
                    "erreur_inf": 1.7274
                  },
                  {
                    "tete_liste": "Jean-Laurent Felizia",
                    "parti": [
                      "EE-LV",
                      "Parti socialiste",
                      "Parti communiste",
                      "Génération·s"
                    ],
                    "intentions": 17,
                    "erreur_sup": 19.8023,
                    "erreur_inf": 14.1977
                  },
                  {
                    "tete_liste": "Valérie Laupies",
                    "parti": {},
                    "intentions": 0.5,
                    "erreur_sup": 1.0262,
                    "erreur_inf": 0
                  },
                  {
                    "tete_liste": "Jean-Marc Governatori",
                    "parti": "Cap écologie",
                    "intentions": 3,
                    "erreur_sup": 4.2726,
                    "erreur_inf": 1.7274
                  },
                  {
                    "tete_liste": "Hervé Guerrera",
                    "parti": {},
                    "intentions": 0.5,
                    "erreur_sup": 1.0262,
                    "erreur_inf": 0
                  }
                ]
              }
            ]
          }
        ]
      },
      {
        "id": "20200825_paca_ifp",
        "nom_institut": "Ifop",
        "debut_enquete": "2020-08-25",
        "fin_enquete": "2020-08-31",
        "commanditaire": "Cap Avenir",
        "lien": "http://www.commission-des-sondages.fr/notices/files/notices/2020/septembre/9076-paca-ifop-nice-matin.pdf",
        "echantillon": 890,
        "population": "Inscrits sur les listes électorales",
        "tours": [
          {
            "tour": "Premier tour",
            "hypotheses": [
              {
                "hypothese": "Hypothèse LR",
                "sous_echantillon": 603.42,
                "tetes_liste": [
                  {
                    "tete_liste": "David Rachline",
                    "parti": "Rassemblement national",
                    "intentions": 29,
                    "erreur_sup": 32.6205,
                    "erreur_inf": 25.3795
                  },
                  {
                    "tete_liste": "Renaud Muselier",
                    "parti": [
                      "Les Républicains",
                      "Modem",
                      "UDI"
                    ],
                    "intentions": 28,
                    "erreur_sup": 31.5825,
                    "erreur_inf": 24.4175
                  },
                  {
                    "tete_liste": "Jean-Marc Governatori",
                    "parti": "Alliance écologiste indépendante",
                    "intentions": 2,
                    "erreur_sup": 3.1171,
                    "erreur_inf": 0.8829
                  },
                  {
                    "tete_liste": "Sophie Camard",
                    "parti": [
                      "Parti communiste",
                      "Parti socialiste",
                      "France insoumise"
                    ],
                    "intentions": 14,
                    "erreur_sup": 16.7686,
                    "erreur_inf": 11.2314
                  },
                  {
                    "tete_liste": null,
                    "parti": "« ext. gauche »",
                    "intentions": 1,
                    "erreur_sup": 1.7939,
                    "erreur_inf": 0.2061
                  },
                  {
                    "tete_liste": "Michèle Rivasi",
                    "parti": "EE-LV",
                    "intentions": 12,
                    "erreur_sup": 14.5929,
                    "erreur_inf": 9.4071
                  },
                  {
                    "tete_liste": "Christophe Castaner",
                    "parti": "LRM",
                    "intentions": 12,
                    "erreur_sup": 14.5929,
                    "erreur_inf": 9.4071
                  }
                ]
              },
              {
                "hypothese": "Hypothèse LR-LRM",
                "sous_echantillon": 590.96,
                "tetes_liste": [
                  {
                    "tete_liste": "Michèle Rivasi",
                    "parti": "EE-LV",
                    "intentions": 14,
                    "erreur_sup": 16.7976,
                    "erreur_inf": 11.2024
                  },
                  {
                    "tete_liste": "David Rachline",
                    "parti": "Rassemblement national",
                    "intentions": 31,
                    "erreur_sup": 34.7289,
                    "erreur_inf": 27.2711
                  },
                  {
                    "tete_liste": "Sophie Camard",
                    "parti": [
                      "Parti communiste",
                      "Parti socialiste",
                      "France insoumise"
                    ],
                    "intentions": 14,
                    "erreur_sup": 16.7976,
                    "erreur_inf": 11.2024
                  },
                  {
                    "tete_liste": "Jean-Marc Governatori",
                    "parti": "Alliance écologiste indépendante",
                    "intentions": 3,
                    "erreur_sup": 4.3754,
                    "erreur_inf": 1.6246
                  },
                  {
                    "tete_liste": "Renaud Muselier",
                    "parti": [
                      "Les Républicains",
                      "Modem",
                      "UDI",
                      "LRM"
                    ],
                    "intentions": 33,
                    "erreur_sup": 36.7912,
                    "erreur_inf": 29.2088
                  },
                  {
                    "tete_liste": null,
                    "parti": "« ext. gauche »",
                    "intentions": 1,
                    "erreur_sup": 1.8022,
                    "erreur_inf": 0.1978
                  }
                ]
              }
            ]
          }
        ]
      },
      {
        "id": "20210526_paca_ifp",
        "nom_institut": "Ifop",
        "debut_enquete": "2021-05-26",
        "fin_enquete": "2021-05-31",
        "commanditaire": "LCI et Le Figaro",
        "lien": "http://www.commission-des-sondages.fr/notices/files/notices/2021/juin/9158-paca-ifop-le-figaro.pdf",
        "echantillon": 1006,
        "population": "Inscrits sur les listes électorales",
        "tours": [
          {
            "tour": "Deuxième tour",
            "hypotheses": [
              {
                "hypothese": "Hypothèse duel",
                "sous_echantillon": 622.714,
                "tetes_liste": [
                  {
                    "tete_liste": "Renaud Muselier",
                    "parti": [
                      "UDI",
                      "Les Républicains",
                      "LRM",
                      "Modem",
                      "Agir"
                    ],
                    "intentions": 51,
                    "erreur_sup": 54.9264,
                    "erreur_inf": 47.0736
                  },
                  {
                    "tete_liste": "Thierry Mariani",
                    "parti": "Rassemblement national",
                    "intentions": 49,
                    "erreur_sup": 52.9264,
                    "erreur_inf": 45.0736
                  }
                ]
              },
              {
                "hypothese": "Hypothèse triangulaire",
                "sous_echantillon": 694.14,
                "tetes_liste": [
                  {
                    "tete_liste": "Renaud Muselier",
                    "parti": [
                      "UDI",
                      "Les Républicains",
                      "LRM",
                      "Modem",
                      "Agir"
                    ],
                    "intentions": 38,
                    "erreur_sup": 41.6109,
                    "erreur_inf": 34.3891
                  },
                  {
                    "tete_liste": "Jean-Laurent Felizia",
                    "parti": [
                      "EE-LV",
                      "Parti socialiste",
                      "Parti communiste",
                      "Génération·s"
                    ],
                    "intentions": 19,
                    "erreur_sup": 21.9184,
                    "erreur_inf": 16.0816
                  },
                  {
                    "tete_liste": "Thierry Mariani",
                    "parti": "Rassemblement national",
                    "intentions": 43,
                    "erreur_sup": 46.683,
                    "erreur_inf": 39.317
                  }
                ]
              }
            ]
          },
          {
            "tour": "Premier tour",
            "hypotheses": [
              {
                "hypothese": null,
                "sous_echantillon": 695.146,
                "tetes_liste": [
                  {
                    "tete_liste": "Jean-Marc Governatori",
                    "parti": "Cap écologie",
                    "intentions": 4,
                    "erreur_sup": 5.4567,
                    "erreur_inf": 2.5433
                  },
                  {
                    "tete_liste": "Thierry Mariani",
                    "parti": "Rassemblement national",
                    "intentions": 39,
                    "erreur_sup": 42.6259,
                    "erreur_inf": 35.3741
                  },
                  {
                    "tete_liste": "Jean-Laurent Felizia",
                    "parti": [
                      "EE-LV",
                      "Parti socialiste",
                      "Parti communiste",
                      "Génération·s"
                    ],
                    "intentions": 15,
                    "erreur_sup": 17.6544,
                    "erreur_inf": 12.3456
                  },
                  {
                    "tete_liste": "Noël Chuisano",
                    "parti": "Debout la France",
                    "intentions": 4,
                    "erreur_sup": 5.4567,
                    "erreur_inf": 2.5433
                  },
                  {
                    "tete_liste": "Isabelle Bonnet",
                    "parti": "Lutte ouvrière",
                    "intentions": 1.5,
                    "erreur_sup": 2.4036,
                    "erreur_inf": 0.5964
                  },
                  {
                    "tete_liste": "Renaud Muselier",
                    "parti": [
                      "UDI",
                      "Les Républicains",
                      "LRM",
                      "Modem",
                      "Agir"
                    ],
                    "intentions": 35,
                    "erreur_sup": 38.5458,
                    "erreur_inf": 31.4542
                  }
                ]
              }
            ]
          }
        ]
      },
      {
        "id": "20210508_paca_ips",
        "nom_institut": "Ipsos",
        "debut_enquete": "2021-05-08",
        "fin_enquete": "2021-05-10",
        "commanditaire": "France Télés et Radio France",
        "lien": "https://www.ipsos.com/fr-fr/regionales-2021-en-provences-alpes-cote-dazur-la-liste-rn-conduite-par-thierry-mariani-se-profile",
        "echantillon": 502,
        "population": "Certains d'aller voter",
        "tours": [
          {
            "tour": "Deuxième tour",
            "hypotheses": [
              {
                "hypothese": "Quadrangulaire",
                "sous_echantillon": 446.78,
                "tetes_liste": [
                  {
                    "tete_liste": "Thierry Mariani",
                    "parti": "Rassemblement national",
                    "intentions": 38,
                    "erreur_sup": 42.5009,
                    "erreur_inf": 33.4991
                  },
                  {
                    "tete_liste": "Renaud Muselier",
                    "parti": [
                      "Les Républicains",
                      "UDI"
                    ],
                    "intentions": 25,
                    "erreur_sup": 29.0152,
                    "erreur_inf": 20.9848
                  },
                  {
                    "tete_liste": "Jean-Laurent Felizia",
                    "parti": [
                      "EE-LV",
                      "Parti socialiste",
                      "Parti communiste",
                      "Génération·s"
                    ],
                    "intentions": 21,
                    "erreur_sup": 24.7769,
                    "erreur_inf": 17.2231
                  },
                  {
                    "tete_liste": "Sophie Cluzel",
                    "parti": [
                      "LRM",
                      "Modem"
                    ],
                    "intentions": 16,
                    "erreur_sup": 19.3995,
                    "erreur_inf": 12.6005
                  }
                ]
              },
              {
                "hypothese": "Triangulaire LR-LRM",
                "sous_echantillon": 431.72,
                "tetes_liste": [
                  {
                    "tete_liste": "Jean-Laurent Felizia",
                    "parti": [
                      "EE-LV",
                      "Parti socialiste",
                      "Parti communiste",
                      "Génération·s"
                    ],
                    "intentions": 24,
                    "erreur_sup": 28.0287,
                    "erreur_inf": 19.9713
                  },
                  {
                    "tete_liste": "Thierry Mariani",
                    "parti": "Rassemblement national",
                    "intentions": 40,
                    "erreur_sup": 44.6213,
                    "erreur_inf": 35.3787
                  },
                  {
                    "tete_liste": "Renaud Muselier",
                    "parti": [
                      "Les Républicains",
                      "UDI",
                      "Modem",
                      "LRM"
                    ],
                    "intentions": 36,
                    "erreur_sup": 40.5279,
                    "erreur_inf": 31.4721
                  }
                ]
              },
              {
                "hypothese": "Triangulaire LR seul",
                "sous_echantillon": 436.74,
                "tetes_liste": [
                  {
                    "tete_liste": "Jean-Laurent Felizia",
                    "parti": [
                      "EE-LV",
                      "Parti socialiste",
                      "Parti communiste",
                      "Génération·s"
                    ],
                    "intentions": 25,
                    "erreur_sup": 29.0611,
                    "erreur_inf": 20.9389
                  },
                  {
                    "tete_liste": "Thierry Mariani",
                    "parti": "Rassemblement national",
                    "intentions": 40,
                    "erreur_sup": 44.5946,
                    "erreur_inf": 35.4054
                  },
                  {
                    "tete_liste": "Renaud Muselier",
                    "parti": [
                      "Les Républicains",
                      "UDI"
                    ],
                    "intentions": 35,
                    "erreur_sup": 39.4734,
                    "erreur_inf": 30.5266
                  }
                ]
              }
            ]
          },
          {
            "tour": "Premier tour",
            "hypotheses": [
              {
                "hypothese": "Union LR-LRM",
                "sous_echantillon": 436.74,
                "tetes_liste": [
                  {
                    "tete_liste": "Isabelle Bonnet",
                    "parti": "Lutte ouvrière",
                    "intentions": 2,
                    "erreur_sup": 3.313,
                    "erreur_inf": 0.687
                  },
                  {
                    "tete_liste": "Thierry Mariani",
                    "parti": "Rassemblement national",
                    "intentions": 39,
                    "erreur_sup": 43.5745,
                    "erreur_inf": 34.4255
                  },
                  {
                    "tete_liste": "Renaud Muselier",
                    "parti": [
                      "Les Républicains",
                      "UDI",
                      "LRM",
                      "Modem"
                    ],
                    "intentions": 34,
                    "erreur_sup": 38.4428,
                    "erreur_inf": 29.5572
                  },
                  {
                    "tete_liste": "Marina Mesure",
                    "parti": "France insoumise",
                    "intentions": 5,
                    "erreur_sup": 7.044,
                    "erreur_inf": 2.956
                  },
                  {
                    "tete_liste": "Jean-Laurent Felizia",
                    "parti": [
                      "EE-LV",
                      "Parti socialiste",
                      "Parti communiste",
                      "Génération·s"
                    ],
                    "intentions": 20,
                    "erreur_sup": 23.7515,
                    "erreur_inf": 16.2485
                  }
                ]
              },
              {
                "hypothese": "LR seul",
                "sous_echantillon": 436.74,
                "tetes_liste": [
                  {
                    "tete_liste": "Jean-Laurent Felizia",
                    "parti": [
                      "EE-LV",
                      "Parti socialiste",
                      "Parti communiste",
                      "Génération·s"
                    ],
                    "intentions": 21,
                    "erreur_sup": 24.82,
                    "erreur_inf": 17.18
                  },
                  {
                    "tete_liste": "Renaud Muselier",
                    "parti": [
                      "Les Républicains",
                      "UDI"
                    ],
                    "intentions": 34,
                    "erreur_sup": 38.4428,
                    "erreur_inf": 29.5572
                  },
                  {
                    "tete_liste": "Isabelle Bonnet",
                    "parti": "Lutte ouvrière",
                    "intentions": 2,
                    "erreur_sup": 3.313,
                    "erreur_inf": 0.687
                  },
                  {
                    "tete_liste": "Thierry Mariani",
                    "parti": "Rassemblement national",
                    "intentions": 38,
                    "erreur_sup": 42.5523,
                    "erreur_inf": 33.4477
                  },
                  {
                    "tete_liste": "Marina Mesure",
                    "parti": "France insoumise",
                    "intentions": 5,
                    "erreur_sup": 7.044,
                    "erreur_inf": 2.956
                  }
                ]
              },
              {
                "hypothese": "LR-LRM distincts",
                "sous_echantillon": 441.76,
                "tetes_liste": [
                  {
                    "tete_liste": "Renaud Muselier",
                    "parti": [
                      "Les Républicains",
                      "UDI"
                    ],
                    "intentions": 22,
                    "erreur_sup": 25.863,
                    "erreur_inf": 18.137
                  },
                  {
                    "tete_liste": "Sophie Cluzel",
                    "parti": [
                      "LRM",
                      "Modem"
                    ],
                    "intentions": 17,
                    "erreur_sup": 20.5029,
                    "erreur_inf": 13.4971
                  },
                  {
                    "tete_liste": "Isabelle Bonnet",
                    "parti": "Lutte ouvrière",
                    "intentions": 2,
                    "erreur_sup": 3.3055,
                    "erreur_inf": 0.6945
                  },
                  {
                    "tete_liste": "Jean-Laurent Felizia",
                    "parti": [
                      "EE-LV",
                      "Parti socialiste",
                      "Parti communiste",
                      "Génération·s"
                    ],
                    "intentions": 17,
                    "erreur_sup": 20.5029,
                    "erreur_inf": 13.4971
                  },
                  {
                    "tete_liste": "Thierry Mariani",
                    "parti": "Rassemblement national",
                    "intentions": 37,
                    "erreur_sup": 41.5023,
                    "erreur_inf": 32.4977
                  },
                  {
                    "tete_liste": "Marina Mesure",
                    "parti": "France insoumise",
                    "intentions": 5,
                    "erreur_sup": 7.0324,
                    "erreur_inf": 2.9676
                  }
                ]
              }
            ]
          }
        ]
      },
      {
        "id": "20210506_paca_ifp",
        "nom_institut": "Ifop",
        "debut_enquete": "2021-05-06",
        "fin_enquete": "2021-05-10",
        "commanditaire": "Le Figaro et LCI",
        "lien": "http://www.commission-des-sondages.fr/notices/files/notices/2021/mai/9134-paca-ifop-le-figarp.pdf",
        "echantillon": 954,
        "population": "Inscrits sur les listes électorales",
        "tours": [
          {
            "tour": "Premier tour",
            "hypotheses": [
              {
                "hypothese": "Hypothèse LRM",
                "sous_echantillon": 673.524,
                "tetes_liste": [
                  {
                    "tete_liste": "Marina Mesure",
                    "parti": "France insoumise",
                    "intentions": 7,
                    "erreur_sup": 8.9269,
                    "erreur_inf": 5.0731
                  },
                  {
                    "tete_liste": "Thierry Mariani",
                    "parti": "Rassemblement national",
                    "intentions": 36,
                    "erreur_sup": 39.6251,
                    "erreur_inf": 32.3749
                  },
                  {
                    "tete_liste": "Sophie Cluzel",
                    "parti": [
                      "LRM",
                      "Modem"
                    ],
                    "intentions": 11,
                    "erreur_sup": 13.363,
                    "erreur_inf": 8.637
                  },
                  {
                    "tete_liste": "Isabelle Bonnet",
                    "parti": "Lutte ouvrière",
                    "intentions": 1,
                    "erreur_sup": 1.7514,
                    "erreur_inf": 0.2486
                  },
                  {
                    "tete_liste": "Renaud Muselier",
                    "parti": [
                      "Les Centristes",
                      "UDI",
                      "Les Républicains"
                    ],
                    "intentions": 27,
                    "erreur_sup": 30.3529,
                    "erreur_inf": 23.6471
                  },
                  {
                    "tete_liste": "Jean-Laurent Felizia",
                    "parti": [
                      "EE-LV",
                      "Parti socialiste",
                      "Parti communiste"
                    ],
                    "intentions": 13,
                    "erreur_sup": 15.5399,
                    "erreur_inf": 10.4601
                  },
                  {
                    "tete_liste": "Noël Chuisano",
                    "parti": "Debout la France",
                    "intentions": 3,
                    "erreur_sup": 4.2883,
                    "erreur_inf": 1.7117
                  }
                ]
              },
              {
                "hypothese": "Hypothèse LR-LRM",
                "sous_echantillon": 677.34,
                "tetes_liste": [
                  {
                    "tete_liste": "Jean-Laurent Felizia",
                    "parti": [
                      "EE-LV",
                      "Parti socialiste",
                      "Parti communiste"
                    ],
                    "intentions": 14,
                    "erreur_sup": 16.6132,
                    "erreur_inf": 11.3868
                  },
                  {
                    "tete_liste": "Marina Mesure",
                    "parti": "France insoumise",
                    "intentions": 7,
                    "erreur_sup": 8.9215,
                    "erreur_inf": 5.0785
                  },
                  {
                    "tete_liste": "Renaud Muselier",
                    "parti": [
                      "Les Centristes",
                      "UDI",
                      "Les Républicains",
                      "LRM",
                      "Modem"
                    ],
                    "intentions": 34,
                    "erreur_sup": 37.5675,
                    "erreur_inf": 30.4325
                  },
                  {
                    "tete_liste": "Isabelle Bonnet",
                    "parti": "Lutte ouvrière",
                    "intentions": 1,
                    "erreur_sup": 1.7493,
                    "erreur_inf": 0.2507
                  },
                  {
                    "tete_liste": "Thierry Mariani",
                    "parti": "Rassemblement national",
                    "intentions": 38,
                    "erreur_sup": 41.6554,
                    "erreur_inf": 34.3446
                  },
                  {
                    "tete_liste": "Noël Chuisano",
                    "parti": "Debout la France",
                    "intentions": 3,
                    "erreur_sup": 4.2847,
                    "erreur_inf": 1.7153
                  }
                ]
              }
            ]
          },
          {
            "tour": "Deuxième tour",
            "hypotheses": [
              {
                "hypothese": "Hypothèse triangulaire",
                "sous_echantillon": 677.34,
                "tetes_liste": [
                  {
                    "tete_liste": "Jean-Laurent Felizia",
                    "parti": [
                      "EE-LV",
                      "Parti socialiste",
                      "Parti communiste"
                    ],
                    "intentions": 20,
                    "erreur_sup": 23.0124,
                    "erreur_inf": 16.9876
                  },
                  {
                    "tete_liste": "Renaud Muselier",
                    "parti": [
                      "Les Centristes",
                      "UDI",
                      "Les Républicains",
                      "LRM",
                      "Modem"
                    ],
                    "intentions": 39,
                    "erreur_sup": 42.6732,
                    "erreur_inf": 35.3268
                  },
                  {
                    "tete_liste": "Thierry Mariani",
                    "parti": "Rassemblement national",
                    "intentions": 41,
                    "erreur_sup": 44.704,
                    "erreur_inf": 37.296
                  }
                ]
              }
            ]
          }
        ]
      },
      {
        "id": "20210406_paca_ifp",
        "nom_institut": "Ifop",
        "debut_enquete": "2021-04-06",
        "fin_enquete": "2021-04-09",
        "commanditaire": "La Tribune et Europe 1",
        "lien": "http://www.commission-des-sondages.fr/notices/files/notices/2021/avril/9118-paca-ifop-la-tribune.pdf",
        "echantillon": 914,
        "population": "Inscrits sur les listes électorales",
        "tours": [
          {
            "tour": "Premier tour",
            "hypotheses": [
              {
                "hypothese": "Hypothèse LR seul",
                "sous_echantillon": 615.122,
                "tetes_liste": [
                  {
                    "tete_liste": "Olivia Fortin",
                    "parti": [
                      "Parti socialiste",
                      "Parti communiste"
                    ],
                    "intentions": 8,
                    "erreur_sup": 10.1439,
                    "erreur_inf": 5.8561
                  },
                  {
                    "tete_liste": "Benoît Kandel",
                    "parti": "Debout la France",
                    "intentions": 4,
                    "erreur_sup": 5.5486,
                    "erreur_inf": 2.4514
                  },
                  {
                    "tete_liste": "Thierry Mariani",
                    "parti": "Rassemblement national",
                    "intentions": 31,
                    "erreur_sup": 34.6549,
                    "erreur_inf": 27.3451
                  },
                  {
                    "tete_liste": null,
                    "parti": "Lutte ouvrière",
                    "intentions": 1,
                    "erreur_sup": 1.7863,
                    "erreur_inf": 0.2137
                  },
                  {
                    "tete_liste": "Renaud Muselier",
                    "parti": [
                      "Les Républicains",
                      "UDI"
                    ],
                    "intentions": 34,
                    "erreur_sup": 37.7436,
                    "erreur_inf": 30.2564
                  },
                  {
                    "tete_liste": "Jean-Laurent Felizia",
                    "parti": "EE-LV",
                    "intentions": 10,
                    "erreur_sup": 12.3708,
                    "erreur_inf": 7.6292
                  },
                  {
                    "tete_liste": "Marina Mesure et Luc Leandri",
                    "parti": "France insoumise",
                    "intentions": 8,
                    "erreur_sup": 10.1439,
                    "erreur_inf": 5.8561
                  }
                ]
              },
              {
                "hypothese": "Hypothèse LRM",
                "sous_echantillon": 618.778,
                "tetes_liste": [
                  {
                    "tete_liste": "Sophie Cluzel",
                    "parti": "LRM",
                    "intentions": 13,
                    "erreur_sup": 15.6498,
                    "erreur_inf": 10.3502
                  },
                  {
                    "tete_liste": "Renaud Muselier",
                    "parti": [
                      "Les Républicains",
                      "UDI"
                    ],
                    "intentions": 27,
                    "erreur_sup": 30.4981,
                    "erreur_inf": 23.5019
                  },
                  {
                    "tete_liste": null,
                    "parti": "Lutte ouvrière",
                    "intentions": 1,
                    "erreur_sup": 1.784,
                    "erreur_inf": 0.216
                  },
                  {
                    "tete_liste": "Olivia Fortin",
                    "parti": [
                      "Parti socialiste",
                      "Parti communiste"
                    ],
                    "intentions": 8,
                    "erreur_sup": 10.1376,
                    "erreur_inf": 5.8624
                  },
                  {
                    "tete_liste": "Jean-Laurent Felizia",
                    "parti": "EE-LV",
                    "intentions": 7,
                    "erreur_sup": 9.0104,
                    "erreur_inf": 4.9896
                  },
                  {
                    "tete_liste": "Marina Mesure et Luc Leandri",
                    "parti": "France insoumise",
                    "intentions": 7,
                    "erreur_sup": 9.0104,
                    "erreur_inf": 4.9896
                  },
                  {
                    "tete_liste": "Benoît Kandel",
                    "parti": "Debout la France",
                    "intentions": 4,
                    "erreur_sup": 5.544,
                    "erreur_inf": 2.456
                  },
                  {
                    "tete_liste": "Thierry Mariani",
                    "parti": "Rassemblement national",
                    "intentions": 31,
                    "erreur_sup": 34.6441,
                    "erreur_inf": 27.3559
                  }
                ]
              }
            ]
          },
          {
            "tour": "Deuxième tour",
            "hypotheses": [
              {
                "hypothese": "Hypothèse triangulaire",
                "sous_echantillon": 578.562,
                "tetes_liste": [
                  {
                    "tete_liste": "Olivia Fortin et Jean-Laurent Felizia",
                    "parti": [
                      "Parti socialiste",
                      "Parti communiste",
                      "EE-LV",
                      "France insoumise"
                    ],
                    "intentions": 24,
                    "erreur_sup": 27.4801,
                    "erreur_inf": 20.5199
                  },
                  {
                    "tete_liste": "Renaud Muselier",
                    "parti": [
                      "Les Républicains",
                      "UDI"
                    ],
                    "intentions": 39,
                    "erreur_sup": 42.9745,
                    "erreur_inf": 35.0255
                  },
                  {
                    "tete_liste": "Thierry Mariani",
                    "parti": "Rassemblement national",
                    "intentions": 37,
                    "erreur_sup": 40.9342,
                    "erreur_inf": 33.0658
                  }
                ]
              }
            ]
          }
        ]
      },
      {
        "id": "20210225_paca_ow",
        "nom_institut": "Opinion Way",
        "debut_enquete": "2021-02-25",
        "fin_enquete": "2021-03-01",
        "commanditaire": "La République en Marche",
        "lien": "https://www.opinion-way.com/fr/component/edocman/opinionway-pour-lrem-intentions-de-vote-pour-les-elections-regionales-2021-en-paca-mars-2021/viewdocument/2542.html?Itemid=0",
        "echantillon": 1003,
        "population": "Inscrits sur les listes électorales",
        "tours": [
          {
            "tour": "Premier tour",
            "hypotheses": [
              {
                "hypothese": "Alliance LR-LRM",
                "sous_echantillon": 762.28,
                "tetes_liste": [
                  {
                    "tete_liste": "Thierry Mariani",
                    "parti": "Rassemblement national",
                    "intentions": 31,
                    "erreur_sup": 34.2833,
                    "erreur_inf": 27.7167
                  },
                  {
                    "tete_liste": "Benoît Kandel",
                    "parti": "Debout la France",
                    "intentions": 6,
                    "erreur_sup": 7.6859,
                    "erreur_inf": 4.3141
                  },
                  {
                    "tete_liste": " Olivia Fortin",
                    "parti": "Parti socialiste",
                    "intentions": 8,
                    "erreur_sup": 9.9259,
                    "erreur_inf": 6.0741
                  },
                  {
                    "tete_liste": "Marina Mesure et Luc Léandri",
                    "parti": "France insoumise",
                    "intentions": 9,
                    "erreur_sup": 11.0316,
                    "erreur_inf": 6.9684
                  },
                  {
                    "tete_liste": "Olivier Dubuquoy",
                    "parti": "EE-LV",
                    "intentions": 11,
                    "erreur_sup": 13.2212,
                    "erreur_inf": 8.7788
                  },
                  {
                    "tete_liste": "Renaud Muselier et Sophie Cluzel",
                    "parti": [
                      "Les Républicains",
                      "UDI",
                      "LRM",
                      "Agir",
                      "Modem"
                    ],
                    "intentions": 30,
                    "erreur_sup": 33.2532,
                    "erreur_inf": 26.7468
                  },
                  {
                    "tete_liste": null,
                    "parti": "« ext. gauche »",
                    "intentions": 1,
                    "erreur_sup": 1.7063,
                    "erreur_inf": 0.2937
                  }
                ]
              },
              {
                "hypothese": "Sophie Cluzel tête de liste LRM",
                "sous_echantillon": 782.34,
                "tetes_liste": [
                  {
                    "tete_liste": "Marina Mesure et Luc Léandri",
                    "parti": "France insoumise",
                    "intentions": 7,
                    "erreur_sup": 8.7879,
                    "erreur_inf": 5.2121
                  },
                  {
                    "tete_liste": "Thierry Mariani",
                    "parti": "Rassemblement national",
                    "intentions": 29,
                    "erreur_sup": 32.1797,
                    "erreur_inf": 25.8203
                  },
                  {
                    "tete_liste": null,
                    "parti": "« ext. gauche »",
                    "intentions": 1,
                    "erreur_sup": 1.6972,
                    "erreur_inf": 0.3028
                  },
                  {
                    "tete_liste": "Benoît Kandel",
                    "parti": "Debout la France",
                    "intentions": 4,
                    "erreur_sup": 5.3732,
                    "erreur_inf": 2.6268
                  },
                  {
                    "tete_liste": "Sophie Cluzel",
                    "parti": [
                      "LRM",
                      "Modem",
                      "Agir"
                    ],
                    "intentions": 16,
                    "erreur_sup": 18.569,
                    "erreur_inf": 13.431
                  },
                  {
                    "tete_liste": "Renaud Muselier",
                    "parti": [
                      "Les Républicains",
                      "UDI"
                    ],
                    "intentions": 23,
                    "erreur_sup": 25.949,
                    "erreur_inf": 20.051
                  },
                  {
                    "tete_liste": " Olivia Fortin",
                    "parti": "Parti socialiste",
                    "intentions": 8,
                    "erreur_sup": 9.9011,
                    "erreur_inf": 6.0989
                  },
                  {
                    "tete_liste": "Olivier Dubuquoy",
                    "parti": "EE-LV",
                    "intentions": 9,
                    "erreur_sup": 11.0054,
                    "erreur_inf": 6.9946
                  }
                ]
              }
            ]
          }
        ]
      },
      {
        "id": "20201203_paca_ifp",
        "nom_institut": "Ifop",
        "debut_enquete": "2020-12-03",
        "fin_enquete": "2020-12-09",
        "commanditaire": "La Tribune et Europe 1",
        "lien": "http://www.commission-des-sondages.fr/notices/files/notices/2021/janvier/9090-paca-ifop-la-tribune.pdf",
        "echantillon": 905,
        "population": "Inscrits sur les listes électorales",
        "tours": [
          {
            "tour": "Premier tour",
            "hypotheses": [
              {
                "hypothese": "Offre éclatée",
                "sous_echantillon": 603.635,
                "tetes_liste": [
                  {
                    "tete_liste": null,
                    "parti": "« ext. gauche »",
                    "intentions": 1,
                    "erreur_sup": 1.7938,
                    "erreur_inf": 0.2062
                  },
                  {
                    "tete_liste": " Benoît Kandel",
                    "parti": "Debout la France",
                    "intentions": 3,
                    "erreur_sup": 4.3609,
                    "erreur_inf": 1.6391
                  },
                  {
                    "tete_liste": "Marina Mesure et Luc Leandri",
                    "parti": "France insoumise",
                    "intentions": 7,
                    "erreur_sup": 9.0354,
                    "erreur_inf": 4.9646
                  },
                  {
                    "tete_liste": "Olivia Fortin",
                    "parti": [
                      "Parti socialiste",
                      "Parti communiste"
                    ],
                    "intentions": 7,
                    "erreur_sup": 9.0354,
                    "erreur_inf": 4.9646
                  },
                  {
                    "tete_liste": " Olivier Dubuquoy ",
                    "parti": "EE-LV",
                    "intentions": 9,
                    "erreur_sup": 11.283,
                    "erreur_inf": 6.717
                  },
                  {
                    "tete_liste": "Jean-Marc Governatori",
                    "parti": "Alliance écologiste indépendante",
                    "intentions": 3,
                    "erreur_sup": 4.3609,
                    "erreur_inf": 1.6391
                  },
                  {
                    "tete_liste": "Renaud Muselier",
                    "parti": [
                      "Les Républicains",
                      "UDI",
                      "Modem"
                    ],
                    "intentions": 26,
                    "erreur_sup": 29.4992,
                    "erreur_inf": 22.5008
                  },
                  {
                    "tete_liste": "Frédérique Vidal",
                    "parti": "LRM",
                    "intentions": 13,
                    "erreur_sup": 15.6829,
                    "erreur_inf": 10.3171
                  },
                  {
                    "tete_liste": "Thierry Mariani",
                    "parti": "Rassemblement national",
                    "intentions": 30,
                    "erreur_sup": 33.6558,
                    "erreur_inf": 26.3442
                  }
                ]
              },
              {
                "hypothese": "Union de la gauche et union des écolos",
                "sous_echantillon": 617.21,
                "tetes_liste": [
                  {
                    "tete_liste": "Frédérique Vidal",
                    "parti": "LRM",
                    "intentions": 13,
                    "erreur_sup": 15.6532,
                    "erreur_inf": 10.3468
                  },
                  {
                    "tete_liste": "Olivia Fortin et Marina Mesure",
                    "parti": [
                      "France insoumise",
                      "Parti communiste",
                      "Parti radical de gauche",
                      "Parti socialiste"
                    ],
                    "intentions": 13,
                    "erreur_sup": 15.6532,
                    "erreur_inf": 10.3468
                  },
                  {
                    "tete_liste": "Renaud Muselier",
                    "parti": [
                      "Les Républicains",
                      "UDI",
                      "Modem"
                    ],
                    "intentions": 27,
                    "erreur_sup": 30.5025,
                    "erreur_inf": 23.4975
                  },
                  {
                    "tete_liste": " Olivier Dubuquoy et JeanMarc Governatori",
                    "parti": [
                      "Alliance écologiste indépendante",
                      "EE-LV"
                    ],
                    "intentions": 11,
                    "erreur_sup": 13.4685,
                    "erreur_inf": 8.5315
                  },
                  {
                    "tete_liste": null,
                    "parti": "« ext. gauche »",
                    "intentions": 1,
                    "erreur_sup": 1.785,
                    "erreur_inf": 0.215
                  },
                  {
                    "tete_liste": " Benoît Kandel",
                    "parti": "Debout la France",
                    "intentions": 3,
                    "erreur_sup": 4.3458,
                    "erreur_inf": 1.6542
                  },
                  {
                    "tete_liste": "Thierry Mariani",
                    "parti": "Rassemblement national",
                    "intentions": 31,
                    "erreur_sup": 34.6488,
                    "erreur_inf": 27.3512
                  }
                ]
              }
            ]
          },
          {
            "tour": "Deuxième tour",
            "hypotheses": [
              {
                "hypothese": "Hypothèse quadrangulaire",
                "sous_echantillon": 600.015,
                "tetes_liste": [
                  {
                    "tete_liste": "Olivier Dubuquoy et Jean-Marc Governatori",
                    "parti": [
                      "EE-LV",
                      "Alliance écologiste indépendante"
                    ],
                    "intentions": 14,
                    "erreur_sup": 16.7764,
                    "erreur_inf": 11.2236
                  },
                  {
                    "tete_liste": "Renaud Muselier",
                    "parti": [
                      "Les Républicains",
                      "Modem",
                      "UDI",
                      "LRM"
                    ],
                    "intentions": 37,
                    "erreur_sup": 40.8632,
                    "erreur_inf": 33.1368
                  },
                  {
                    "tete_liste": "Thierry Mariani",
                    "parti": "Rassemblement national",
                    "intentions": 34,
                    "erreur_sup": 37.7904,
                    "erreur_inf": 30.2096
                  },
                  {
                    "tete_liste": "Olivia Fortin et Marina Mesure",
                    "parti": [
                      "France insoumise",
                      "Parti socialiste",
                      "Parti radical de gauche",
                      "Parti communiste"
                    ],
                    "intentions": 15,
                    "erreur_sup": 17.8571,
                    "erreur_inf": 12.1429
                  }
                ]
              },
              {
                "hypothese": "Hypothèse triangulaire",
                "sous_echantillon": 591.87,
                "tetes_liste": [
                  {
                    "tete_liste": "Thierry Mariani",
                    "parti": "Rassemblement national",
                    "intentions": 37,
                    "erreur_sup": 40.8897,
                    "erreur_inf": 33.1103
                  },
                  {
                    "tete_liste": "Renaud Muselier",
                    "parti": [
                      "Les Républicains",
                      "Modem",
                      "LRM",
                      "UDI"
                    ],
                    "intentions": 40,
                    "erreur_sup": 43.9468,
                    "erreur_inf": 36.0532
                  },
                  {
                    "tete_liste": "Olivier Fortin et Olivier Dubuquoy",
                    "parti": [
                      "France insoumise",
                      "Parti socialiste",
                      "EE-LV",
                      "Parti communiste"
                    ],
                    "intentions": 23,
                    "erreur_sup": 26.3904,
                    "erreur_inf": 19.6096
                  }
                ]
              }
            ]
          }
        ]
      },
      {
        "id": "20210607_paca_ow",
        "nom_institut": "Opinion Way",
        "debut_enquete": "2021-06-07",
        "fin_enquete": "2021-06-10",
        "commanditaire": "CNews",
        "lien": "https://www.opinion-way.com/fr/component/edocman/opinionway-pour-cnews-les-intentions-de-vote-pour-l-election-regionale-en-paca-vague-2-11-juin-2021/viewdocument/2603.html?Itemid=0",
        "echantillon": 1067,
        "population": "Inscrits sur les listes électorales",
        "tours": [
          {
            "tour": "Premier tour",
            "hypotheses": [
              {
                "hypothese": null,
                "sous_echantillon": 821.59,
                "tetes_liste": [
                  {
                    "tete_liste": "Isabelle Bonnet",
                    "parti": "Lutte ouvrière",
                    "intentions": 1,
                    "erreur_sup": 1.6804,
                    "erreur_inf": 0.3196
                  },
                  {
                    "tete_liste": "Thierry Mariani",
                    "parti": "Rassemblement national",
                    "intentions": 43,
                    "erreur_sup": 46.3853,
                    "erreur_inf": 39.6147
                  },
                  {
                    "tete_liste": "Valérie Laupies",
                    "parti": {},
                    "intentions": 1,
                    "erreur_sup": 1.6804,
                    "erreur_inf": 0.3196
                  },
                  {
                    "tete_liste": "Renaud Muselier",
                    "parti": [
                      "UDI",
                      "Les Républicains",
                      "LRM",
                      "Modem",
                      "Agir"
                    ],
                    "intentions": 32,
                    "erreur_sup": 35.1898,
                    "erreur_inf": 28.8102
                  },
                  {
                    "tete_liste": "Jean-Laurent Felizia",
                    "parti": [
                      "EE-LV",
                      "Parti socialiste",
                      "Parti communiste",
                      "Génération·s"
                    ],
                    "intentions": 17,
                    "erreur_sup": 19.5686,
                    "erreur_inf": 14.4314
                  },
                  {
                    "tete_liste": "Mikael Vicenzi",
                    "parti": {},
                    "intentions": 0.5,
                    "erreur_sup": 0.9823,
                    "erreur_inf": 0.0177
                  },
                  {
                    "tete_liste": "Jean-Marc Governatori",
                    "parti": "Cap écologie",
                    "intentions": 3,
                    "erreur_sup": 4.1665,
                    "erreur_inf": 1.8335
                  },
                  {
                    "tete_liste": "Noël Chuisano",
                    "parti": "Debout la France",
                    "intentions": 2,
                    "erreur_sup": 2.9573,
                    "erreur_inf": 1.0427
                  },
                  {
                    "tete_liste": "Hervé Guerrera",
                    "parti": {},
                    "intentions": 1,
                    "erreur_sup": 1.6804,
                    "erreur_inf": 0.3196
                  }
                ]
              }
            ]
          },
          {
            "tour": "Deuxième tour",
            "hypotheses": [
              {
                "hypothese": "Hypothèse triangulaire",
                "sous_echantillon": 800.25,
                "tetes_liste": [
                  {
                    "tete_liste": "Jean-Laurent Felizia",
                    "parti": [
                      "EE-LV",
                      "Parti socialiste",
                      "Parti communiste",
                      "Génération·s"
                    ],
                    "intentions": 21,
                    "erreur_sup": 23.8221,
                    "erreur_inf": 18.1779
                  },
                  {
                    "tete_liste": "Thierry Mariani",
                    "parti": "Rassemblement national",
                    "intentions": 46,
                    "erreur_sup": 49.4532,
                    "erreur_inf": 42.5468
                  },
                  {
                    "tete_liste": "Renaud Muselier",
                    "parti": [
                      "UDI",
                      "Les Républicains",
                      "LRM",
                      "Modem",
                      "Agir"
                    ],
                    "intentions": 33,
                    "erreur_sup": 36.2579,
                    "erreur_inf": 29.7421
                  }
                ]
              },
              {
                "hypothese": "Hypothèse duel",
                "sous_echantillon": 704.22,
                "tetes_liste": [
                  {
                    "tete_liste": "Thierry Mariani",
                    "parti": "Rassemblement national",
                    "intentions": 52,
                    "erreur_sup": 55.69,
                    "erreur_inf": 48.31
                  },
                  {
                    "tete_liste": "Renaud Muselier",
                    "parti": [
                      "UDI",
                      "Les Républicains",
                      "LRM",
                      "Modem",
                      "Agir"
                    ],
                    "intentions": 48,
                    "erreur_sup": 51.69,
                    "erreur_inf": 44.31
                  }
                ]
              }
            ]
          }
        ]
      },
      {
        "id": "20210531_paca_ow",
        "nom_institut": "Opinion Way",
        "debut_enquete": "2021-05-31",
        "fin_enquete": "2021-06-03",
        "commanditaire": "CNews",
        "lien": "http://www.commission-des-sondages.fr/notices/files/notices/2021/juin/9154-paca-ow-c-news.pdf",
        "echantillon": 1004,
        "population": "Inscrits sur les listes électorales",
        "tours": [
          {
            "tour": "Premier tour",
            "hypotheses": [
              {
                "hypothese": null,
                "sous_echantillon": 732.92,
                "tetes_liste": [
                  {
                    "tete_liste": "Isabelle Bonnet",
                    "parti": "Lutte ouvrière",
                    "intentions": 1,
                    "erreur_sup": 1.7204,
                    "erreur_inf": 0.2796
                  },
                  {
                    "tete_liste": "Thierry Mariani",
                    "parti": "Rassemblement national",
                    "intentions": 42,
                    "erreur_sup": 45.5733,
                    "erreur_inf": 38.4267
                  },
                  {
                    "tete_liste": "Jean-Laurent Felizia",
                    "parti": [
                      "EE-LV",
                      "Parti socialiste",
                      "Parti communiste",
                      "Génération·s"
                    ],
                    "intentions": 16,
                    "erreur_sup": 18.6542,
                    "erreur_inf": 13.3458
                  },
                  {
                    "tete_liste": "Noël Chuisano",
                    "parti": "Debout la France",
                    "intentions": 4,
                    "erreur_sup": 5.4187,
                    "erreur_inf": 2.5813
                  },
                  {
                    "tete_liste": "Renaud Muselier",
                    "parti": [
                      "UDI",
                      "Les Républicains",
                      "LRM",
                      "Modem",
                      "Agir"
                    ],
                    "intentions": 32,
                    "erreur_sup": 35.3772,
                    "erreur_inf": 28.6228
                  },
                  {
                    "tete_liste": "Jean-Marc Governatori",
                    "parti": "Cap écologie",
                    "intentions": 4,
                    "erreur_sup": 5.4187,
                    "erreur_inf": 2.5813
                  }
                ]
              }
            ]
          },
          {
            "tour": "Deuxième tour",
            "hypotheses": [
              {
                "hypothese": "Hypothèse sans la gauche",
                "sous_echantillon": 642.56,
                "tetes_liste": [
                  {
                    "tete_liste": "Renaud Muselier",
                    "parti": [
                      "UDI",
                      "Les Républicains",
                      "LRM",
                      "Modem",
                      "Agir"
                    ],
                    "intentions": 48,
                    "erreur_sup": 51.863,
                    "erreur_inf": 44.137
                  },
                  {
                    "tete_liste": "Thierry Mariani",
                    "parti": "Rassemblement national",
                    "intentions": 52,
                    "erreur_sup": 55.863,
                    "erreur_inf": 48.137
                  }
                ]
              },
              {
                "hypothese": "Hypothèse avec la gauche",
                "sous_echantillon": 742.96,
                "tetes_liste": [
                  {
                    "tete_liste": "Renaud Muselier",
                    "parti": [
                      "UDI",
                      "Les Républicains",
                      "LRM",
                      "Modem",
                      "Agir"
                    ],
                    "intentions": 34,
                    "erreur_sup": 37.4063,
                    "erreur_inf": 30.5937
                  },
                  {
                    "tete_liste": "Thierry Mariani",
                    "parti": "Rassemblement national",
                    "intentions": 45,
                    "erreur_sup": 48.5773,
                    "erreur_inf": 41.4227
                  },
                  {
                    "tete_liste": "Jean-Laurent Felizia",
                    "parti": [
                      "EE-LV",
                      "Parti socialiste",
                      "Parti communiste",
                      "Génération·s"
                    ],
                    "intentions": 21,
                    "erreur_sup": 23.9288,
                    "erreur_inf": 18.0712
                  }
                ]
              }
            ]
          }
        ]
      },
      {
        "id": "20210521_paca_elb",
        "nom_institut": "Elabe",
        "debut_enquete": "2021-05-21",
        "fin_enquete": "2021-05-26",
        "commanditaire": "BFM",
        "lien": "http://www.commission-des-sondages.fr/notices/files/notices/2021/mai/9143-paca-elabe-bfmtv.pdf",
        "echantillon": 582,
        "population": "Certains d'aller voter",
        "tours": [
          {
            "tour": "Premier tour",
            "hypotheses": [
              {
                "hypothese": null,
                "sous_echantillon": 506.34,
                "tetes_liste": [
                  {
                    "tete_liste": "Jean-Marc Governatori",
                    "parti": "Cap écologie",
                    "intentions": 6,
                    "erreur_sup": 8.0686,
                    "erreur_inf": 3.9314
                  },
                  {
                    "tete_liste": "Jean-Laurent Felizia",
                    "parti": [
                      "EE-LV",
                      "Parti socialiste",
                      "Parti communiste",
                      "Génération·s"
                    ],
                    "intentions": 12,
                    "erreur_sup": 14.8305,
                    "erreur_inf": 9.1695
                  },
                  {
                    "tete_liste": "Noël Chuisano",
                    "parti": "Debout la France",
                    "intentions": 2,
                    "erreur_sup": 3.2194,
                    "erreur_inf": 0.7806
                  },
                  {
                    "tete_liste": "Thierry Mariani",
                    "parti": "Rassemblement national",
                    "intentions": 43,
                    "erreur_sup": 47.3123,
                    "erreur_inf": 38.6877
                  },
                  {
                    "tete_liste": "Renaud Muselier",
                    "parti": [
                      "UDI",
                      "Les Républicains",
                      "LRM",
                      "Modem",
                      "Agir"
                    ],
                    "intentions": 33,
                    "erreur_sup": 37.0957,
                    "erreur_inf": 28.9043
                  },
                  {
                    "tete_liste": "Isabelle Bonnet",
                    "parti": "Lutte ouvrière",
                    "intentions": 2,
                    "erreur_sup": 3.2194,
                    "erreur_inf": 0.7806
                  }
                ]
              }
            ]
          },
          {
            "tour": "Deuxième tour",
            "hypotheses": [
              {
                "hypothese": "Hypothèse triangulaire",
                "sous_echantillon": 512.16,
                "tetes_liste": [
                  {
                    "tete_liste": "Thierry Mariani",
                    "parti": "Rassemblement national",
                    "intentions": 45,
                    "erreur_sup": 49.3086,
                    "erreur_inf": 40.6914
                  },
                  {
                    "tete_liste": "Renaud Muselier",
                    "parti": [
                      "UDI",
                      "Les Républicains",
                      "LRM",
                      "Modem",
                      "Agir"
                    ],
                    "intentions": 37,
                    "erreur_sup": 41.1814,
                    "erreur_inf": 32.8186
                  },
                  {
                    "tete_liste": "Jean-Laurent Felizia",
                    "parti": [
                      "EE-LV",
                      "Parti socialiste",
                      "Parti communiste",
                      "Génération·s"
                    ],
                    "intentions": 18,
                    "erreur_sup": 21.3273,
                    "erreur_inf": 14.6727
                  }
                ]
              },
              {
                "hypothese": "Hypothèse duel",
                "sous_echantillon": 483.06,
                "tetes_liste": [
                  {
                    "tete_liste": "Thierry Mariani",
                    "parti": "Rassemblement national",
                    "intentions": 50,
                    "erreur_sup": 54.4589,
                    "erreur_inf": 45.5411
                  },
                  {
                    "tete_liste": "Renaud Muselier",
                    "parti": [
                      "UDI",
                      "Les Républicains",
                      "LRM",
                      "Modem",
                      "Agir"
                    ],
                    "intentions": 50,
                    "erreur_sup": 54.4589,
                    "erreur_inf": 45.5411
                  }
                ]
              }
            ]
          }
        ]
      }
    ]
  }
]
